<?xml version="1.0" encoding="UTF-8"?>
<con:soapui-project id="dab8e6a2-2360-4970-8e62-f00de38d2a86" created="3.57.0" activeEnvironment="Default environment" encryptionMode="Not encrypted" name="Activity3" projectVersion="" updated="3.57.0 2024-12-10T10:59:20Z" xmlns:con="http://eviware.com/soapui/config">
  <con:settings/>
  <con:interface xsi:type="con:WsdlInterface" id="682baa9c-6dee-4fbb-a1ea-e65bc161722f" wsaVersion="NONE" name="CalculatorSoap12" type="wsdl" bindingName="{http://tempuri.org/}CalculatorSoap12" soapVersion="1_2" anonymous="optional" definition="http://www.dneonline.com/calculator.asmx?wsdl" xmlns:xsi="http://www.w3.org/2001/XMLSchema-instance">
    <con:settings id="8d1eedbc-c42d-4c94-bd36-36fa3af6098d"/>
    <con:definitionCache type="TEXT" rootPart="http://www.dneonline.com/calculator.asmx?wsdl">
      <con:part>
        <con:url>http://www.dneonline.com/calculator.asmx?wsdl</con:url>
        <con:content><![CDATA[<wsdl:definitions targetNamespace="http://tempuri.org/" xmlns:soap="http://schemas.xmlsoap.org/wsdl/soap/" xmlns:tm="http://microsoft.com/wsdl/mime/textMatching/" xmlns:soapenc="http://schemas.xmlsoap.org/soap/encoding/" xmlns:mime="http://schemas.xmlsoap.org/wsdl/mime/" xmlns:tns="http://tempuri.org/" xmlns:s="http://www.w3.org/2001/XMLSchema" xmlns:soap12="http://schemas.xmlsoap.org/wsdl/soap12/" xmlns:http="http://schemas.xmlsoap.org/wsdl/http/" xmlns:wsdl="http://schemas.xmlsoap.org/wsdl/">
  <wsdl:types>
    <s:schema elementFormDefault="qualified" targetNamespace="http://tempuri.org/">
      <s:element name="Add">
        <s:complexType>
          <s:sequence>
            <s:element minOccurs="1" maxOccurs="1" name="intA" type="s:int"/>
            <s:element minOccurs="1" maxOccurs="1" name="intB" type="s:int"/>
          </s:sequence>
        </s:complexType>
      </s:element>
      <s:element name="AddResponse">
        <s:complexType>
          <s:sequence>
            <s:element minOccurs="1" maxOccurs="1" name="AddResult" type="s:int"/>
          </s:sequence>
        </s:complexType>
      </s:element>
      <s:element name="Subtract">
        <s:complexType>
          <s:sequence>
            <s:element minOccurs="1" maxOccurs="1" name="intA" type="s:int"/>
            <s:element minOccurs="1" maxOccurs="1" name="intB" type="s:int"/>
          </s:sequence>
        </s:complexType>
      </s:element>
      <s:element name="SubtractResponse">
        <s:complexType>
          <s:sequence>
            <s:element minOccurs="1" maxOccurs="1" name="SubtractResult" type="s:int"/>
          </s:sequence>
        </s:complexType>
      </s:element>
      <s:element name="Multiply">
        <s:complexType>
          <s:sequence>
            <s:element minOccurs="1" maxOccurs="1" name="intA" type="s:int"/>
            <s:element minOccurs="1" maxOccurs="1" name="intB" type="s:int"/>
          </s:sequence>
        </s:complexType>
      </s:element>
      <s:element name="MultiplyResponse">
        <s:complexType>
          <s:sequence>
            <s:element minOccurs="1" maxOccurs="1" name="MultiplyResult" type="s:int"/>
          </s:sequence>
        </s:complexType>
      </s:element>
      <s:element name="Divide">
        <s:complexType>
          <s:sequence>
            <s:element minOccurs="1" maxOccurs="1" name="intA" type="s:int"/>
            <s:element minOccurs="1" maxOccurs="1" name="intB" type="s:int"/>
          </s:sequence>
        </s:complexType>
      </s:element>
      <s:element name="DivideResponse">
        <s:complexType>
          <s:sequence>
            <s:element minOccurs="1" maxOccurs="1" name="DivideResult" type="s:int"/>
          </s:sequence>
        </s:complexType>
      </s:element>
    </s:schema>
  </wsdl:types>
  <wsdl:message name="AddSoapIn">
    <wsdl:part name="parameters" element="tns:Add"/>
  </wsdl:message>
  <wsdl:message name="AddSoapOut">
    <wsdl:part name="parameters" element="tns:AddResponse"/>
  </wsdl:message>
  <wsdl:message name="SubtractSoapIn">
    <wsdl:part name="parameters" element="tns:Subtract"/>
  </wsdl:message>
  <wsdl:message name="SubtractSoapOut">
    <wsdl:part name="parameters" element="tns:SubtractResponse"/>
  </wsdl:message>
  <wsdl:message name="MultiplySoapIn">
    <wsdl:part name="parameters" element="tns:Multiply"/>
  </wsdl:message>
  <wsdl:message name="MultiplySoapOut">
    <wsdl:part name="parameters" element="tns:MultiplyResponse"/>
  </wsdl:message>
  <wsdl:message name="DivideSoapIn">
    <wsdl:part name="parameters" element="tns:Divide"/>
  </wsdl:message>
  <wsdl:message name="DivideSoapOut">
    <wsdl:part name="parameters" element="tns:DivideResponse"/>
  </wsdl:message>
  <wsdl:portType name="CalculatorSoap">
    <wsdl:operation name="Add">
      <wsdl:documentation>Adds two integers. This is a test WebService. ©DNE Online</wsdl:documentation>
      <wsdl:input message="tns:AddSoapIn"/>
      <wsdl:output message="tns:AddSoapOut"/>
    </wsdl:operation>
    <wsdl:operation name="Subtract">
      <wsdl:input message="tns:SubtractSoapIn"/>
      <wsdl:output message="tns:SubtractSoapOut"/>
    </wsdl:operation>
    <wsdl:operation name="Multiply">
      <wsdl:input message="tns:MultiplySoapIn"/>
      <wsdl:output message="tns:MultiplySoapOut"/>
    </wsdl:operation>
    <wsdl:operation name="Divide">
      <wsdl:input message="tns:DivideSoapIn"/>
      <wsdl:output message="tns:DivideSoapOut"/>
    </wsdl:operation>
  </wsdl:portType>
  <wsdl:binding name="CalculatorSoap" type="tns:CalculatorSoap">
    <soap:binding transport="http://schemas.xmlsoap.org/soap/http"/>
    <wsdl:operation name="Add">
      <soap:operation soapAction="http://tempuri.org/Add" style="document"/>
      <wsdl:input>
        <soap:body use="literal"/>
      </wsdl:input>
      <wsdl:output>
        <soap:body use="literal"/>
      </wsdl:output>
    </wsdl:operation>
    <wsdl:operation name="Subtract">
      <soap:operation soapAction="http://tempuri.org/Subtract" style="document"/>
      <wsdl:input>
        <soap:body use="literal"/>
      </wsdl:input>
      <wsdl:output>
        <soap:body use="literal"/>
      </wsdl:output>
    </wsdl:operation>
    <wsdl:operation name="Multiply">
      <soap:operation soapAction="http://tempuri.org/Multiply" style="document"/>
      <wsdl:input>
        <soap:body use="literal"/>
      </wsdl:input>
      <wsdl:output>
        <soap:body use="literal"/>
      </wsdl:output>
    </wsdl:operation>
    <wsdl:operation name="Divide">
      <soap:operation soapAction="http://tempuri.org/Divide" style="document"/>
      <wsdl:input>
        <soap:body use="literal"/>
      </wsdl:input>
      <wsdl:output>
        <soap:body use="literal"/>
      </wsdl:output>
    </wsdl:operation>
  </wsdl:binding>
  <wsdl:binding name="CalculatorSoap12" type="tns:CalculatorSoap">
    <soap12:binding transport="http://schemas.xmlsoap.org/soap/http"/>
    <wsdl:operation name="Add">
      <soap12:operation soapAction="http://tempuri.org/Add" style="document"/>
      <wsdl:input>
        <soap12:body use="literal"/>
      </wsdl:input>
      <wsdl:output>
        <soap12:body use="literal"/>
      </wsdl:output>
    </wsdl:operation>
    <wsdl:operation name="Subtract">
      <soap12:operation soapAction="http://tempuri.org/Subtract" style="document"/>
      <wsdl:input>
        <soap12:body use="literal"/>
      </wsdl:input>
      <wsdl:output>
        <soap12:body use="literal"/>
      </wsdl:output>
    </wsdl:operation>
    <wsdl:operation name="Multiply">
      <soap12:operation soapAction="http://tempuri.org/Multiply" style="document"/>
      <wsdl:input>
        <soap12:body use="literal"/>
      </wsdl:input>
      <wsdl:output>
        <soap12:body use="literal"/>
      </wsdl:output>
    </wsdl:operation>
    <wsdl:operation name="Divide">
      <soap12:operation soapAction="http://tempuri.org/Divide" style="document"/>
      <wsdl:input>
        <soap12:body use="literal"/>
      </wsdl:input>
      <wsdl:output>
        <soap12:body use="literal"/>
      </wsdl:output>
    </wsdl:operation>
  </wsdl:binding>
  <wsdl:service name="Calculator">
    <wsdl:port name="CalculatorSoap" binding="tns:CalculatorSoap">
      <soap:address location="http://www.dneonline.com/calculator.asmx"/>
    </wsdl:port>
    <wsdl:port name="CalculatorSoap12" binding="tns:CalculatorSoap12">
      <soap12:address location="http://www.dneonline.com/calculator.asmx"/>
    </wsdl:port>
  </wsdl:service>
</wsdl:definitions>]]></con:content>
        <con:type>http://schemas.xmlsoap.org/wsdl/</con:type>
      </con:part>
    </con:definitionCache>
    <con:endpoints>
      <con:endpoint>http://www.dneonline.com/calculator.asmx</con:endpoint>
    </con:endpoints>
    <con:operation id="6725be0b-fcaf-4ff0-92e0-e5ed77dfd692" isOneWay="false" action="http://tempuri.org/Add" name="Add" bindingOperationName="Add" type="Request-Response" inputName="" receivesAttachments="false" sendsAttachments="false" anonymous="optional">
      <con:settings/>
      <con:call id="f1571d0b-d141-4028-a7cf-409cc6c1b142" name="Add Request">
        <con:settings>
          <con:setting id="com.eviware.soapui.impl.wsdl.WsdlRequest@request-headers">&lt;xml-fragment/></con:setting>
        </con:settings>
        <con:encoding>UTF-8</con:encoding>
        <con:endpoint>http://www.dneonline.com/calculator.asmx</con:endpoint>
        <con:request><![CDATA[<soap:Envelope xmlns:soap="http://www.w3.org/2003/05/soap-envelope" xmlns:tem="http://tempuri.org/">
   <soap:Header/>
   <soap:Body>
      <tem:Add>
         <tem:intA>18</tem:intA>
         <tem:intB>39</tem:intB>
      </tem:Add>
   </soap:Body>
</soap:Envelope>]]></con:request>
        <con:credentials>
          <con:selectedAuthProfile>No Authorization</con:selectedAuthProfile>
          <con:authType>No Authorization</con:authType>
        </con:credentials>
        <con:jmsConfig JMSDeliveryMode="PERSISTENT"/>
        <con:wsaConfig mustUnderstand="NONE" version="200508" action="http://tempuri.org/CalculatorSoap/AddRequest"/>
        <con:wsrmConfig version="1.2"/>
      </con:call>
    </con:operation>
    <con:operation id="787c3358-46af-4dd8-be83-de5bdd11af51" isOneWay="false" action="http://tempuri.org/Divide" name="Divide" bindingOperationName="Divide" type="Request-Response" inputName="" receivesAttachments="false" sendsAttachments="false" anonymous="optional">
      <con:settings/>
      <con:call id="298ab0ec-7612-4b29-b5e9-bc879875a2d7" name="Divide Request">
        <con:settings/>
        <con:encoding>UTF-8</con:encoding>
        <con:endpoint>http://www.dneonline.com/calculator.asmx</con:endpoint>
        <con:request><![CDATA[<soap:Envelope xmlns:soap="http://www.w3.org/2003/05/soap-envelope" xmlns:tem="http://tempuri.org/">\r
   <soap:Header/>\r
   <soap:Body>\r
      <tem:Divide>\r
         <tem:intA>?</tem:intA>\r
         <tem:intB>?</tem:intB>\r
      </tem:Divide>\r
   </soap:Body>\r
</soap:Envelope>]]></con:request>
        <con:credentials>
          <con:selectedAuthProfile>No Authorization</con:selectedAuthProfile>
          <con:authType>No Authorization</con:authType>
        </con:credentials>
        <con:wsaConfig mustUnderstand="NONE" version="200508" action="http://tempuri.org/CalculatorSoap/DivideRequest"/>
      </con:call>
    </con:operation>
    <con:operation id="d21ec03f-5706-4670-8379-241ae7b831ac" isOneWay="false" action="http://tempuri.org/Multiply" name="Multiply" bindingOperationName="Multiply" type="Request-Response" inputName="" receivesAttachments="false" sendsAttachments="false" anonymous="optional">
      <con:settings/>
      <con:call id="2ade7003-d8f8-439a-9a3d-01618174a547" name="Multiply Request">
        <con:settings/>
        <con:encoding>UTF-8</con:encoding>
        <con:endpoint>http://www.dneonline.com/calculator.asmx</con:endpoint>
        <con:request><![CDATA[<soap:Envelope xmlns:soap="http://www.w3.org/2003/05/soap-envelope" xmlns:tem="http://tempuri.org/">\r
   <soap:Header/>\r
   <soap:Body>\r
      <tem:Multiply>\r
         <tem:intA>?</tem:intA>\r
         <tem:intB>?</tem:intB>\r
      </tem:Multiply>\r
   </soap:Body>\r
</soap:Envelope>]]></con:request>
        <con:credentials>
          <con:selectedAuthProfile>No Authorization</con:selectedAuthProfile>
          <con:authType>No Authorization</con:authType>
        </con:credentials>
        <con:wsaConfig mustUnderstand="NONE" version="200508" action="http://tempuri.org/CalculatorSoap/MultiplyRequest"/>
      </con:call>
    </con:operation>
    <con:operation id="7935511b-26e4-446c-aa54-a1ac0303cdd2" isOneWay="false" action="http://tempuri.org/Subtract" name="Subtract" bindingOperationName="Subtract" type="Request-Response" inputName="" receivesAttachments="false" sendsAttachments="false" anonymous="optional">
      <con:settings/>
      <con:call id="99011ab2-c925-4e7f-93e2-f77757604f2e" name="Subtract Request">
        <con:settings/>
        <con:encoding>UTF-8</con:encoding>
        <con:endpoint>http://www.dneonline.com/calculator.asmx</con:endpoint>
        <con:request><![CDATA[<soap:Envelope xmlns:soap="http://www.w3.org/2003/05/soap-envelope" xmlns:tem="http://tempuri.org/">\r
   <soap:Header/>\r
   <soap:Body>\r
      <tem:Subtract>\r
         <tem:intA>?</tem:intA>\r
         <tem:intB>?</tem:intB>\r
      </tem:Subtract>\r
   </soap:Body>\r
</soap:Envelope>]]></con:request>
        <con:credentials>
          <con:selectedAuthProfile>No Authorization</con:selectedAuthProfile>
          <con:authType>No Authorization</con:authType>
        </con:credentials>
        <con:wsaConfig mustUnderstand="NONE" version="200508" action="http://tempuri.org/CalculatorSoap/SubtractRequest"/>
      </con:call>
    </con:operation>
  </con:interface>
  <con:interface xsi:type="con:WsdlInterface" id="c0a3bb69-481d-4d27-b235-124fa7a60e6e" wsaVersion="NONE" name="CalculatorSoap" type="wsdl" bindingName="{http://tempuri.org/}CalculatorSoap" soapVersion="1_1" anonymous="optional" definition="http://www.dneonline.com/calculator.asmx?wsdl" xmlns:xsi="http://www.w3.org/2001/XMLSchema-instance">
    <con:settings id="4cedb65d-9b9e-4a14-87e1-65c088fee62a"/>
    <con:definitionCache/>
    <con:endpoints>
      <con:endpoint>http://www.dneonline.com/calculator.asmx</con:endpoint>
    </con:endpoints>
    <con:operation id="3388cf9c-a448-436b-ba10-77fe8083cfdc" isOneWay="false" action="http://tempuri.org/Add" name="Add" bindingOperationName="Add" type="Request-Response" inputName="" receivesAttachments="false" sendsAttachments="false" anonymous="optional">
      <con:settings/>
      <con:call id="4366f906-c4e1-40ac-ad19-1b21de16de05" name="Add Request">
        <con:settings/>
        <con:encoding>UTF-8</con:encoding>
        <con:endpoint>http://www.dneonline.com/calculator.asmx</con:endpoint>
        <con:request><![CDATA[<soapenv:Envelope xmlns:soapenv="http://schemas.xmlsoap.org/soap/envelope/" xmlns:tem="http://tempuri.org/">\r
   <soapenv:Header/>\r
   <soapenv:Body>\r
      <tem:Add>\r
         <tem:intA>?</tem:intA>\r
         <tem:intB>?</tem:intB>\r
      </tem:Add>\r
   </soapenv:Body>\r
</soapenv:Envelope>]]></con:request>
        <con:credentials>
          <con:selectedAuthProfile>No Authorization</con:selectedAuthProfile>
          <con:authType>No Authorization</con:authType>
        </con:credentials>
        <con:wsaConfig mustUnderstand="NONE" version="200508" action="http://tempuri.org/Add"/>
      </con:call>
    </con:operation>
    <con:operation id="9daea614-2f6f-457c-9a0a-34837548c9af" isOneWay="false" action="http://tempuri.org/Divide" name="Divide" bindingOperationName="Divide" type="Request-Response" inputName="" receivesAttachments="false" sendsAttachments="false" anonymous="optional">
      <con:settings/>
      <con:call id="f57c1ce3-3e52-41e2-af46-43010b3a68d8" name="Divide Request">
        <con:settings/>
        <con:encoding>UTF-8</con:encoding>
        <con:endpoint>http://www.dneonline.com/calculator.asmx</con:endpoint>
        <con:request><![CDATA[<soapenv:Envelope xmlns:soapenv="http://schemas.xmlsoap.org/soap/envelope/" xmlns:tem="http://tempuri.org/">\r
   <soapenv:Header/>\r
   <soapenv:Body>\r
      <tem:Divide>\r
         <tem:intA>?</tem:intA>\r
         <tem:intB>?</tem:intB>\r
      </tem:Divide>\r
   </soapenv:Body>\r
</soapenv:Envelope>]]></con:request>
        <con:credentials>
          <con:selectedAuthProfile>No Authorization</con:selectedAuthProfile>
          <con:authType>No Authorization</con:authType>
        </con:credentials>
        <con:wsaConfig mustUnderstand="NONE" version="200508" action="http://tempuri.org/Divide"/>
      </con:call>
    </con:operation>
    <con:operation id="b4b46b28-21a8-4b97-aadf-0ea4d94fc194" isOneWay="false" action="http://tempuri.org/Multiply" name="Multiply" bindingOperationName="Multiply" type="Request-Response" inputName="" receivesAttachments="false" sendsAttachments="false" anonymous="optional">
      <con:settings/>
      <con:call id="e8f443d6-e3e8-4583-9112-13f8c46bf899" name="Multiply Request">
        <con:settings/>
        <con:encoding>UTF-8</con:encoding>
        <con:endpoint>http://www.dneonline.com/calculator.asmx</con:endpoint>
        <con:request><![CDATA[<soapenv:Envelope xmlns:soapenv="http://schemas.xmlsoap.org/soap/envelope/" xmlns:tem="http://tempuri.org/">\r
   <soapenv:Header/>\r
   <soapenv:Body>\r
      <tem:Multiply>\r
         <tem:intA>?</tem:intA>\r
         <tem:intB>?</tem:intB>\r
      </tem:Multiply>\r
   </soapenv:Body>\r
</soapenv:Envelope>]]></con:request>
        <con:credentials>
          <con:selectedAuthProfile>No Authorization</con:selectedAuthProfile>
          <con:authType>No Authorization</con:authType>
        </con:credentials>
        <con:wsaConfig mustUnderstand="NONE" version="200508" action="http://tempuri.org/Multiply"/>
      </con:call>
    </con:operation>
    <con:operation id="eeb82c4b-89dc-42ae-8966-d54de3bcb06c" isOneWay="false" action="http://tempuri.org/Subtract" name="Subtract" bindingOperationName="Subtract" type="Request-Response" inputName="" receivesAttachments="false" sendsAttachments="false" anonymous="optional">
      <con:settings/>
      <con:call id="f3269049-8f00-4e4c-8c7f-cd24d98b8675" name="Subtract Request">
        <con:settings/>
        <con:encoding>UTF-8</con:encoding>
        <con:endpoint>http://www.dneonline.com/calculator.asmx</con:endpoint>
        <con:request><![CDATA[<soapenv:Envelope xmlns:soapenv="http://schemas.xmlsoap.org/soap/envelope/" xmlns:tem="http://tempuri.org/">\r
   <soapenv:Header/>\r
   <soapenv:Body>\r
      <tem:Subtract>\r
         <tem:intA>?</tem:intA>\r
         <tem:intB>?</tem:intB>\r
      </tem:Subtract>\r
   </soapenv:Body>\r
</soapenv:Envelope>]]></con:request>
        <con:credentials>
          <con:selectedAuthProfile>No Authorization</con:selectedAuthProfile>
          <con:authType>No Authorization</con:authType>
        </con:credentials>
        <con:wsaConfig mustUnderstand="NONE" version="200508" action="http://tempuri.org/Subtract"/>
      </con:call>
    </con:operation>
  </con:interface>
  <con:testSuite id="ea67fd08-331c-490f-a830-253eae178b43" name="Project 1 Test Suite 1">
    <con:settings id="f341f5ce-e766-4d8e-9533-7477412ef706"/>
    <con:runType>SEQUENTIAL</con:runType>
    <con:testCase id="516f609a-542e-4a4a-85e8-825b17191340" discardOkResults="false" failOnError="false" failTestCaseOnErrors="true" keepSession="false" name="Project 1 Test Case 1" searchProperties="true" timeout="0">
      <con:settings/>
      <con:testStep type="request" id="31b639e4-8e6a-47b3-b4c5-a595a4d3fd1d" name="CalculatorSoap12 Add-Add Request">
        <con:settings/>
        <con:config xsi:type="con:RequestStep" xmlns:xsi="http://www.w3.org/2001/XMLSchema-instance">
          <con:interface>CalculatorSoap12</con:interface>
          <con:operation>Add</con:operation>
          <con:request name="CalculatorSoap12 Add-Add Request" outgoingWss="" incomingWss="" timeout="" sslKeystore="" useWsAddressing="false" useWsReliableMessaging="false" wssPasswordType="" id="b16e221c-06bf-40ba-aa96-32e264b4905a">
            <con:settings>
              <con:setting id="com.eviware.soapui.impl.wsdl.WsdlRequest@request-headers">&lt;xml-fragment/></con:setting>
            </con:settings>
            <con:encoding>UTF-8</con:encoding>
            <con:endpoint>http://www.dneonline.com/calculator.asmx</con:endpoint>
            <con:request><![CDATA[<soap:Envelope xmlns:soap="http://www.w3.org/2003/05/soap-envelope" xmlns:tem="http://tempuri.org/">
   <soap:Header/>
   <soap:Body>
      <tem:Add>
         <tem:intA>98</tem:intA>
         <tem:intB>278</tem:intB>
      </tem:Add>
   </soap:Body>
</soap:Envelope>]]></con:request>
            <con:assertion type="SOAP Response" id="c9281c75-287b-4f1a-b286-b45a331c35cc" name="SOAP Response"/>
            <con:assertion type="Valid HTTP Status Codes" id="d7ee85f4-9991-454d-856a-a685cea782ed" name="Valid HTTP Status Codes">
              <con:settings/>
              <con:configuration>
                <codes>200</codes>
              </con:configuration>
            </con:assertion>
            <con:assertion type="Schema Compliance" id="05357556-2e79-4834-944e-0ee1d70181e5" name="Schema Compliance">
              <con:configuration/>
            </con:assertion>
            <con:assertion type="SOAP Fault Assertion" id="f623d772-4d2b-4315-b9a3-b2aafc2e5494" name="Not SOAP Fault"/>
            <con:assertion type="XPath Match" id="8ad4082b-0bbc-4731-8cb8-3f5d274f6e21" name="XPath Match">
              <con:configuration>
                <path>declare namespace ns1='http://tempuri.org/';
//ns1:AddResponse[1]/ns1:AddResult[1]</path>
                <content>376</content>
                <allowWildcards>false</allowWildcards>
                <ignoreNamspaceDifferences>false</ignoreNamspaceDifferences>
                <ignoreComments>false</ignoreComments>
              </con:configuration>
            </con:assertion>
            <con:credentials>
              <con:selectedAuthProfile>No Authorization</con:selectedAuthProfile>
              <con:authType>No Authorization</con:authType>
            </con:credentials>
            <con:jmsConfig JMSDeliveryMode="PERSISTENT"/>
            <con:wsaConfig mustUnderstand="NONE" version="200508" action="http://tempuri.org/CalculatorSoap/AddRequest"/>
            <con:wsrmConfig version="1.2"/>
          </con:request>
        </con:config>
      </con:testStep>
      <con:testStep type="request" id="cb03bd1e-ea17-4ccc-8afc-278b9a19066c" name="CalculatorSoap12 Divide-Divide Request">
        <con:settings/>
        <con:config xsi:type="con:RequestStep" xmlns:xsi="http://www.w3.org/2001/XMLSchema-instance">
          <con:interface>CalculatorSoap12</con:interface>
          <con:operation>Divide</con:operation>
          <con:request name="CalculatorSoap12 Divide-Divide Request" outgoingWss="" incomingWss="" timeout="" sslKeystore="" useWsAddressing="false" useWsReliableMessaging="false" wssPasswordType="" id="d0da9ae9-1d33-4865-8109-f77a5d298768">
            <con:settings/>
            <con:encoding>UTF-8</con:encoding>
            <con:endpoint>http://www.dneonline.com/calculator.asmx</con:endpoint>
            <con:request><![CDATA[<soap:Envelope xmlns:soap="http://www.w3.org/2003/05/soap-envelope" xmlns:tem="http://tempuri.org/">\r
   <soap:Header/>\r
   <soap:Body>\r
      <tem:Divide>\r
         <tem:intA>?</tem:intA>\r
         <tem:intB>?</tem:intB>\r
      </tem:Divide>\r
   </soap:Body>\r
</soap:Envelope>]]></con:request>
            <con:assertion type="SOAP Response" id="b505e70b-6e58-4f63-8934-4e2ee8da01b6" name="SOAP Response"/>
            <con:assertion type="Valid HTTP Status Codes" id="42d38181-a6dc-4bfe-9611-e44c33a47c21" name="Valid HTTP Status Codes">
              <con:settings/>
              <con:configuration>
                <codes>200</codes>
              </con:configuration>
            </con:assertion>
            <con:assertion type="Schema Compliance" id="9b45edc6-f7cc-49fe-9f16-4cd034dc33ca" name="Schema Compliance">
              <con:configuration/>
            </con:assertion>
            <con:assertion type="Response SLA Assertion" id="ee5c709a-7337-4c82-9043-f9f7088ac45f" name="Response SLA">
              <con:configuration>
                <SLA>200</SLA>
              </con:configuration>
            </con:assertion>
            <con:assertion type="SOAP Fault Assertion" id="5565cfb4-68e6-4089-98e0-bfa0d4b49812" name="Not SOAP Fault"/>
            <con:credentials>
              <con:selectedAuthProfile>No Authorization</con:selectedAuthProfile>
              <con:authType>No Authorization</con:authType>
            </con:credentials>
            <con:wsaConfig mustUnderstand="NONE" version="200508" action="http://tempuri.org/CalculatorSoap/DivideRequest"/>
          </con:request>
        </con:config>
      </con:testStep>
      <con:testStep type="request" id="46cb8a02-0513-45d7-9604-fb3fb8d44026" name="CalculatorSoap12 Multiply-Multiply Request">
        <con:settings/>
        <con:config xsi:type="con:RequestStep" xmlns:xsi="http://www.w3.org/2001/XMLSchema-instance">
          <con:interface>CalculatorSoap12</con:interface>
          <con:operation>Multiply</con:operation>
          <con:request name="CalculatorSoap12 Multiply-Multiply Request" outgoingWss="" incomingWss="" timeout="" sslKeystore="" useWsAddressing="false" useWsReliableMessaging="false" wssPasswordType="" id="3b15bebd-9c10-4ddc-a454-938a27092bc3">
            <con:settings/>
            <con:encoding>UTF-8</con:encoding>
            <con:endpoint>http://www.dneonline.com/calculator.asmx</con:endpoint>
            <con:request><![CDATA[<soap:Envelope xmlns:soap="http://www.w3.org/2003/05/soap-envelope" xmlns:tem="http://tempuri.org/">\r
   <soap:Header/>\r
   <soap:Body>\r
      <tem:Multiply>\r
         <tem:intA>?</tem:intA>\r
         <tem:intB>?</tem:intB>\r
      </tem:Multiply>\r
   </soap:Body>\r
</soap:Envelope>]]></con:request>
            <con:assertion type="SOAP Response" id="b21c3a14-0938-4dc5-b89b-bccf984ae7a1" name="SOAP Response"/>
            <con:assertion type="Valid HTTP Status Codes" id="f942f40d-4893-422e-b715-672615d5bdda" name="Valid HTTP Status Codes">
              <con:settings/>
              <con:configuration>
                <codes>200</codes>
              </con:configuration>
            </con:assertion>
            <con:assertion type="Schema Compliance" id="34fd6c64-78d5-410e-be79-16214ff1c407" name="Schema Compliance">
              <con:configuration/>
            </con:assertion>
            <con:assertion type="Response SLA Assertion" id="c35dcbc4-0e1f-419e-8b7b-1b9e664fb0a6" name="Response SLA">
              <con:configuration>
                <SLA>200</SLA>
              </con:configuration>
            </con:assertion>
            <con:assertion type="SOAP Fault Assertion" id="83cc9597-6a9d-40f4-9911-385bc9f70e32" name="Not SOAP Fault"/>
            <con:credentials>
              <con:selectedAuthProfile>No Authorization</con:selectedAuthProfile>
              <con:authType>No Authorization</con:authType>
            </con:credentials>
            <con:wsaConfig mustUnderstand="NONE" version="200508" action="http://tempuri.org/CalculatorSoap/MultiplyRequest"/>
          </con:request>
        </con:config>
      </con:testStep>
      <con:testStep type="request" id="a84b0822-7b2a-4937-905c-9d5496e737e9" name="CalculatorSoap12 Subtract-Subtract Request">
        <con:settings/>
        <con:config xsi:type="con:RequestStep" xmlns:xsi="http://www.w3.org/2001/XMLSchema-instance">
          <con:interface>CalculatorSoap12</con:interface>
          <con:operation>Subtract</con:operation>
          <con:request name="CalculatorSoap12 Subtract-Subtract Request" outgoingWss="" incomingWss="" timeout="" sslKeystore="" useWsAddressing="false" useWsReliableMessaging="false" wssPasswordType="" id="bcf6fb06-01a9-4c2a-be97-2a5ee141ad02">
            <con:settings/>
            <con:encoding>UTF-8</con:encoding>
            <con:endpoint>http://www.dneonline.com/calculator.asmx</con:endpoint>
            <con:request><![CDATA[<soap:Envelope xmlns:soap="http://www.w3.org/2003/05/soap-envelope" xmlns:tem="http://tempuri.org/">\r
   <soap:Header/>\r
   <soap:Body>\r
      <tem:Subtract>\r
         <tem:intA>?</tem:intA>\r
         <tem:intB>?</tem:intB>\r
      </tem:Subtract>\r
   </soap:Body>\r
</soap:Envelope>]]></con:request>
            <con:assertion type="SOAP Response" id="4a8c76b3-99c2-4ab4-874b-beebc0a47fb6" name="SOAP Response"/>
            <con:assertion type="Valid HTTP Status Codes" id="e175f454-967a-47ce-9a61-802011288b91" name="Valid HTTP Status Codes">
              <con:settings/>
              <con:configuration>
                <codes>200</codes>
              </con:configuration>
            </con:assertion>
            <con:assertion type="Schema Compliance" id="2367c7f2-4992-46ac-b5e8-117aa0460aea" name="Schema Compliance">
              <con:configuration/>
            </con:assertion>
            <con:assertion type="Response SLA Assertion" id="2b69dbda-79ff-4345-8200-ffca02c3f05e" name="Response SLA">
              <con:configuration>
                <SLA>200</SLA>
              </con:configuration>
            </con:assertion>
            <con:assertion type="SOAP Fault Assertion" id="a839e274-9a7f-497a-b723-5e1a3d01505f" name="Not SOAP Fault"/>
            <con:credentials>
              <con:selectedAuthProfile>No Authorization</con:selectedAuthProfile>
              <con:authType>No Authorization</con:authType>
            </con:credentials>
            <con:wsaConfig mustUnderstand="NONE" version="200508" action="http://tempuri.org/CalculatorSoap/SubtractRequest"/>
          </con:request>
        </con:config>
      </con:testStep>
      <con:testStep type="request" id="e8febc02-ad73-42ce-96e0-2c5197e94cb2" name="CalculatorSoap Add-Add Request">
        <con:settings/>
        <con:config xsi:type="con:RequestStep" xmlns:xsi="http://www.w3.org/2001/XMLSchema-instance">
          <con:interface>CalculatorSoap</con:interface>
          <con:operation>Add</con:operation>
          <con:request name="CalculatorSoap Add-Add Request" outgoingWss="" incomingWss="" timeout="" sslKeystore="" useWsAddressing="false" useWsReliableMessaging="false" wssPasswordType="" id="4b686b9d-49ec-4e29-a4b9-f6061b700d1d">
            <con:settings/>
            <con:encoding>UTF-8</con:encoding>
            <con:endpoint>http://www.dneonline.com/calculator.asmx</con:endpoint>
            <con:request><![CDATA[<soapenv:Envelope xmlns:soapenv="http://schemas.xmlsoap.org/soap/envelope/" xmlns:tem="http://tempuri.org/">\r
   <soapenv:Header/>\r
   <soapenv:Body>\r
      <tem:Add>\r
         <tem:intA>?</tem:intA>\r
         <tem:intB>?</tem:intB>\r
      </tem:Add>\r
   </soapenv:Body>\r
</soapenv:Envelope>]]></con:request>
            <con:assertion type="SOAP Response" id="53eae0d8-d1a1-4015-9675-1950c62c9702" name="SOAP Response"/>
            <con:assertion type="Valid HTTP Status Codes" id="b55a1a5b-2a61-4763-9151-4b70dfa35ad3" name="Valid HTTP Status Codes">
              <con:settings/>
              <con:configuration>
                <codes>200</codes>
              </con:configuration>
            </con:assertion>
            <con:assertion type="Schema Compliance" id="b86be9a5-7dad-4f8d-985e-2fddbab14fc5" name="Schema Compliance">
              <con:configuration/>
            </con:assertion>
            <con:assertion type="Response SLA Assertion" id="43725c2a-5eec-496c-9bb2-af589bf0ddd1" name="Response SLA">
              <con:configuration>
                <SLA>200</SLA>
              </con:configuration>
            </con:assertion>
            <con:assertion type="SOAP Fault Assertion" id="fd287a32-c362-4f49-b9c9-f8aab64c266a" name="Not SOAP Fault"/>
            <con:credentials>
              <con:selectedAuthProfile>No Authorization</con:selectedAuthProfile>
              <con:authType>No Authorization</con:authType>
            </con:credentials>
            <con:wsaConfig mustUnderstand="NONE" version="200508" action="http://tempuri.org/Add"/>
          </con:request>
        </con:config>
      </con:testStep>
      <con:testStep type="request" id="5c482b72-16b6-47f9-a758-e1be690f2ec4" name="CalculatorSoap Divide-Divide Request">
        <con:settings/>
        <con:config xsi:type="con:RequestStep" xmlns:xsi="http://www.w3.org/2001/XMLSchema-instance">
          <con:interface>CalculatorSoap</con:interface>
          <con:operation>Divide</con:operation>
          <con:request name="CalculatorSoap Divide-Divide Request" outgoingWss="" incomingWss="" timeout="" sslKeystore="" useWsAddressing="false" useWsReliableMessaging="false" wssPasswordType="" id="ea2d717e-20eb-46b0-a3c3-faa1d932b773">
            <con:settings/>
            <con:encoding>UTF-8</con:encoding>
            <con:endpoint>http://www.dneonline.com/calculator.asmx</con:endpoint>
            <con:request><![CDATA[<soapenv:Envelope xmlns:soapenv="http://schemas.xmlsoap.org/soap/envelope/" xmlns:tem="http://tempuri.org/">\r
   <soapenv:Header/>\r
   <soapenv:Body>\r
      <tem:Divide>\r
         <tem:intA>?</tem:intA>\r
         <tem:intB>?</tem:intB>\r
      </tem:Divide>\r
   </soapenv:Body>\r
</soapenv:Envelope>]]></con:request>
            <con:assertion type="SOAP Response" id="8592015d-77f6-43dd-b039-efe88b5f8517" name="SOAP Response"/>
            <con:assertion type="Valid HTTP Status Codes" id="8bb06c24-07c4-44b1-8c7c-98b00b8b459a" name="Valid HTTP Status Codes">
              <con:settings/>
              <con:configuration>
                <codes>200</codes>
              </con:configuration>
            </con:assertion>
            <con:assertion type="Schema Compliance" id="c4e67331-2f87-4e4c-b3ed-1def34caa672" name="Schema Compliance">
              <con:configuration/>
            </con:assertion>
            <con:assertion type="Response SLA Assertion" id="285895bb-1820-4a63-b88c-f7e3501e45c1" name="Response SLA">
              <con:configuration>
                <SLA>200</SLA>
              </con:configuration>
            </con:assertion>
            <con:assertion type="SOAP Fault Assertion" id="b397d5a3-57ae-47a4-967d-8eb6c1812ea0" name="Not SOAP Fault"/>
            <con:credentials>
              <con:selectedAuthProfile>No Authorization</con:selectedAuthProfile>
              <con:authType>No Authorization</con:authType>
            </con:credentials>
            <con:wsaConfig mustUnderstand="NONE" version="200508" action="http://tempuri.org/Divide"/>
          </con:request>
        </con:config>
      </con:testStep>
      <con:testStep type="request" id="9d2fd44f-3505-45e2-8480-df0fbb2100d9" name="CalculatorSoap Multiply-Multiply Request">
        <con:settings/>
        <con:config xsi:type="con:RequestStep" xmlns:xsi="http://www.w3.org/2001/XMLSchema-instance">
          <con:interface>CalculatorSoap</con:interface>
          <con:operation>Multiply</con:operation>
          <con:request name="CalculatorSoap Multiply-Multiply Request" outgoingWss="" incomingWss="" timeout="" sslKeystore="" useWsAddressing="false" useWsReliableMessaging="false" wssPasswordType="" id="8724f5ed-b7c7-41dc-b950-9c3c9101e84f">
            <con:settings/>
            <con:encoding>UTF-8</con:encoding>
            <con:endpoint>http://www.dneonline.com/calculator.asmx</con:endpoint>
            <con:request><![CDATA[<soapenv:Envelope xmlns:soapenv="http://schemas.xmlsoap.org/soap/envelope/" xmlns:tem="http://tempuri.org/">\r
   <soapenv:Header/>\r
   <soapenv:Body>\r
      <tem:Multiply>\r
         <tem:intA>?</tem:intA>\r
         <tem:intB>?</tem:intB>\r
      </tem:Multiply>\r
   </soapenv:Body>\r
</soapenv:Envelope>]]></con:request>
            <con:assertion type="SOAP Response" id="72853540-5857-4864-bd37-801d5cc85e4f" name="SOAP Response"/>
            <con:assertion type="Valid HTTP Status Codes" id="e8b68946-8803-4c2d-bd2f-25a177c3e11d" name="Valid HTTP Status Codes">
              <con:settings/>
              <con:configuration>
                <codes>200</codes>
              </con:configuration>
            </con:assertion>
            <con:assertion type="Schema Compliance" id="af2351da-6ada-475b-aad3-fa3622370500" name="Schema Compliance">
              <con:configuration/>
            </con:assertion>
            <con:assertion type="Response SLA Assertion" id="487dcba7-1666-4cf6-8622-7ddabb9d1ebe" name="Response SLA">
              <con:configuration>
                <SLA>200</SLA>
              </con:configuration>
            </con:assertion>
            <con:assertion type="SOAP Fault Assertion" id="4b3a1595-0d03-4bab-8f47-083bb1dffeff" name="Not SOAP Fault"/>
            <con:credentials>
              <con:selectedAuthProfile>No Authorization</con:selectedAuthProfile>
              <con:authType>No Authorization</con:authType>
            </con:credentials>
            <con:wsaConfig mustUnderstand="NONE" version="200508" action="http://tempuri.org/Multiply"/>
          </con:request>
        </con:config>
      </con:testStep>
      <con:testStep type="request" id="8c7254ed-0d50-4d7a-8aa6-227d501384f3" name="CalculatorSoap Subtract-Subtract Request">
        <con:settings/>
        <con:config xsi:type="con:RequestStep" xmlns:xsi="http://www.w3.org/2001/XMLSchema-instance">
          <con:interface>CalculatorSoap</con:interface>
          <con:operation>Subtract</con:operation>
          <con:request name="CalculatorSoap Subtract-Subtract Request" outgoingWss="" incomingWss="" timeout="" sslKeystore="" useWsAddressing="false" useWsReliableMessaging="false" wssPasswordType="" id="78fc991e-1073-4cea-9c2c-b8b7afc2ccc6">
            <con:settings/>
            <con:encoding>UTF-8</con:encoding>
            <con:endpoint>http://www.dneonline.com/calculator.asmx</con:endpoint>
            <con:request><![CDATA[<soapenv:Envelope xmlns:soapenv="http://schemas.xmlsoap.org/soap/envelope/" xmlns:tem="http://tempuri.org/">\r
   <soapenv:Header/>\r
   <soapenv:Body>\r
      <tem:Subtract>\r
         <tem:intA>?</tem:intA>\r
         <tem:intB>?</tem:intB>\r
      </tem:Subtract>\r
   </soapenv:Body>\r
</soapenv:Envelope>]]></con:request>
            <con:assertion type="SOAP Response" id="1436b94d-c2ec-4bd0-afbe-1a5d940c60b1" name="SOAP Response"/>
            <con:assertion type="Valid HTTP Status Codes" id="137f3245-e4b2-4945-9d94-e2e7f799cc4c" name="Valid HTTP Status Codes">
              <con:settings/>
              <con:configuration>
                <codes>200</codes>
              </con:configuration>
            </con:assertion>
            <con:assertion type="Schema Compliance" id="d21fe1aa-96bd-4bac-9182-88761f3a13c0" name="Schema Compliance">
              <con:configuration/>
            </con:assertion>
            <con:assertion type="Response SLA Assertion" id="b6a7cfb1-ffd2-41b1-80d1-b53799433d7a" name="Response SLA">
              <con:configuration>
                <SLA>200</SLA>
              </con:configuration>
            </con:assertion>
            <con:assertion type="SOAP Fault Assertion" id="6439cbf8-3363-41d0-bcbb-28e221d90899" name="Not SOAP Fault"/>
            <con:credentials>
              <con:selectedAuthProfile>No Authorization</con:selectedAuthProfile>
              <con:authType>No Authorization</con:authType>
            </con:credentials>
            <con:jmsConfig JMSDeliveryMode="PERSISTENT"/>
            <con:wsaConfig mustUnderstand="NONE" version="200508" action="http://tempuri.org/Subtract"/>
            <con:wsrmConfig version="1.2"/>
          </con:request>
        </con:config>
      </con:testStep>
      <con:properties/>
      <con:reportParameters/>
    </con:testCase>
    <con:properties/>
    <con:reportParameters/>
  </con:testSuite>
  <con:properties/>
  <con:wssContainer/>
  <con:databaseConnectionContainer/>
  <con:jmsConnectionContainer/>
  <con:oAuth2ProfileContainer/>
  <con:oAuth1ProfileContainer/>
  <con:reporting>
    <con:xmlTemplates/>
    <con:parameters/>
  </con:reporting>
  <con:eventHandlers type="RequestFilter.filterRequest" name="RequestFilter.filterRequest">
    <con:script>// Sample event script to add custom HTTP header to all outgoing REST, SOAP and HTTP(S) calls
// This code is often used for adding custom authentication to ReadyAPI functional tests

// If hardcoding the token, uncomment and change line 5
// token = '4567'

// If your token is parameterized in Project level custom property, uncomment line 8
// token = request.parent.testCase.testSuite.project.getProperty('auth_token').getValue()

// To modify all outgoing calls, remove comments from lines 11 to 16
// headers = request.requestHeaders
// if (headers.containsKey('auth_token2') == false) {
//   headers.put('auth_token2', token)
//   request.requestHeaders = headers
// }</con:script>
  </con:eventHandlers>
  <con:eventHandlers type="TestRunListener.afterStep" name="TestRunListener.afterStep">
    <con:script>// Save all test step results into files
// Change the directory path in line 5 to a location where you want to store details
// then uncomment lines 5 to 10

// filePath = 'C:\\tempOutputDirectory\\'
// fos = new java.io.FileOutputStream(filePath + testStepResult.testStep.label + '.txt', true)
// pw = new java.io.PrintWriter(fos)
// testStepResult.writeTo(pw)
// pw.close()
// fos.close()</con:script>
  </con:eventHandlers>
  <con:authRepository/>
  <con:tags/>
</con:soapui-project>
